MANIFEST.in
README.md
setup.py
bin/stmcli
stmcli/__init__.py
stmcli/bus.py
stmcli/data.py
stmcli/database.py
stmcli/metro.py
stmcli/models.py
stmcli.egg-info/PKG-INFO
stmcli.egg-info/SOURCES.txt
stmcli.egg-info/dependency_links.txt
stmcli.egg-info/requires.txt
stmcli.egg-info/top_level.txt