Metadata-Version: 1.1
Name: stmcli
Version: 1.0.4
Summary: The unofficial STM CLI client.
Home-page: https://github.com/stmcli/stmcli
Author: Pascal Boardman / Philippe Dagenais
Author-email: pascalboardman@gmail.com
License: MIT
Keywords: stm montreal autobus bus schedule horaire
Platform: UNKNOWN
Classifier: Development Status :: 4 - Beta
Classifier: Intended Audience :: End Users/Desktop
Classifier: License :: OSI Approved :: MIT License
Classifier: Programming Language :: Python :: 3
Classifier: Programming Language :: Python :: 3.3
Classifier: Programming Language :: Python :: 3.4
Classifier: Programming Language :: Python :: 3.5
